kami/__init__.py
kami/client.py
kami/exceptions.py
kami/types.py
kami_client-1.2.2.dist-info/METADATA
kami_client-1.2.2.dist-info/WHEEL
kami_client-1.2.2.dist-info/top_level.txt
kami_client-1.2.2.dist-info/RECORD
